{
"type": "FeatureCollection",
"name": "8504312",
"crs": { "type": "name", "properties": { "name": "urn:ogc:def:crs:OGC:1.3:CRS84" } },
"features": [
{ "type": "Feature", "properties": { "number": "8504300", "designationOfficial": "Biel/Bienne" }, "geometry": { "type": "Point", "coordinates": [ 7.24291060323, 47.132897870859999 ] } },
{ "type": "Feature", "properties": { "number": "8504303", "designationOfficial": "La Heutte" }, "geometry": { "type": "Point", "coordinates": [ 7.22539578099, 47.189491807700001 ] } },
{ "type": "Feature", "properties": { "number": "8504302", "designationOfficial": "Reuchenette-Péry" }, "geometry": { "type": "Point", "coordinates": [ 7.24702472889, 47.189739101470003 ] } },
{ "type": "Feature", "properties": { "number": "8504305", "designationOfficial": "Corgémont" }, "geometry": { "type": "Point", "coordinates": [ 7.14466145967, 47.193398767959998 ] } },
{ "type": "Feature", "properties": { "number": "8504304", "designationOfficial": "Sonceboz-Sombeval" }, "geometry": { "type": "Point", "coordinates": [ 7.16876357856, 47.195148357180003 ] } },
{ "type": "Feature", "properties": { "number": "8504307", "designationOfficial": "Courtelary" }, "geometry": { "type": "Point", "coordinates": [ 7.06880326998, 47.175631543309997 ] } },
{ "type": "Feature", "properties": { "number": "8504306", "designationOfficial": "Cortébert" }, "geometry": { "type": "Point", "coordinates": [ 7.10730920432, 47.189337148180002 ] } },
{ "type": "Feature", "properties": { "number": "8504309", "designationOfficial": "Villeret" }, "geometry": { "type": "Point", "coordinates": [ 7.0196751732, 47.160203683410003 ] } },
{ "type": "Feature", "properties": { "number": "8504308", "designationOfficial": "Cormoret" }, "geometry": { "type": "Point", "coordinates": [ 7.05412356821, 47.172947099319998 ] } },
{ "type": "Feature", "properties": { "number": "8504311", "designationOfficial": "Sonvilier" }, "geometry": { "type": "Point", "coordinates": [ 6.96935277867, 47.141342118639997 ] } },
{ "type": "Feature", "properties": { "number": "8504310", "designationOfficial": "St-Imier" }, "geometry": { "type": "Point", "coordinates": [ 7.00122388741, 47.151711081160002 ] } },
{ "type": "Feature", "properties": { "number": "8504312", "designationOfficial": "Renan BE" }, "geometry": { "type": "Point", "coordinates": [ 6.92538209047, 47.125720456739998 ] } },
{ "type": "Feature", "properties": { "number": "8504314", "designationOfficial": "La Chaux-de-Fonds" }, "geometry": { "type": "Point", "coordinates": [ 6.82598272105, 47.098374355479997 ] } },
{ "type": "Feature", "properties": { "number": "8504301", "designationOfficial": "Frinvillier-Taubenloch" }, "geometry": { "type": "Point", "coordinates": [ 7.25752927622, 47.169457796590002 ] } }
]
}
