{
"type": "FeatureCollection",
"name": "8504441",
"crs": { "type": "name", "properties": { "name": "urn:ogc:def:crs:OGC:1.3:CRS84" } },
"features": [
{ "type": "Feature", "properties": { "number": "8504300", "designationOfficial": "Biel/Bienne" }, "geometry": { "type": "Point", "coordinates": [ 7.24291060323, 47.132897870859999 ] } },
{ "type": "Feature", "properties": { "number": "8504108", "designationOfficial": "Bern Europaplatz" }, "geometry": { "type": "Point", "coordinates": [ 7.40611755507, 46.944209832920002 ] } },
{ "type": "Feature", "properties": { "number": "8504411", "designationOfficial": "Münchenbuchsee" }, "geometry": { "type": "Point", "coordinates": [ 7.45194766971, 47.021375785609997 ] } },
{ "type": "Feature", "properties": { "number": "8504410", "designationOfficial": "Zollikofen" }, "geometry": { "type": "Point", "coordinates": [ 7.46291119582, 47.001825935440003 ] } },
{ "type": "Feature", "properties": { "number": "8504413", "designationOfficial": "Suberg-Grossaffoltern" }, "geometry": { "type": "Point", "coordinates": [ 7.3390048549, 47.058782114869999 ] } },
{ "type": "Feature", "properties": { "number": "8504412", "designationOfficial": "Schüpfen" }, "geometry": { "type": "Point", "coordinates": [ 7.38600196021, 47.041859592450002 ] } },
{ "type": "Feature", "properties": { "number": "8504415", "designationOfficial": "Busswil BE" }, "geometry": { "type": "Point", "coordinates": [ 7.31862288564, 47.098684850989997 ] } },
{ "type": "Feature", "properties": { "number": "8504414", "designationOfficial": "Lyss" }, "geometry": { "type": "Point", "coordinates": [ 7.30630154849, 47.076323503929999 ] } },
{ "type": "Feature", "properties": { "number": "8504416", "designationOfficial": "Brügg BE" }, "geometry": { "type": "Point", "coordinates": [ 7.27822199136, 47.123639525489999 ] } },
{ "type": "Feature", "properties": { "number": "8507077", "designationOfficial": "Kehrsatz" }, "geometry": { "type": "Point", "coordinates": [ 7.47236023762, 46.908822992479998 ] } },
{ "type": "Feature", "properties": { "number": "8507093", "designationOfficial": "Kehrsatz Nord" }, "geometry": { "type": "Point", "coordinates": [ 7.46610906448, 46.915836368340003 ] } },
{ "type": "Feature", "properties": { "number": "8507092", "designationOfficial": "Belp Steinbach" }, "geometry": { "type": "Point", "coordinates": [ 7.49309180319, 46.895164634060002 ] } },
{ "type": "Feature", "properties": { "number": "8507076", "designationOfficial": "Belp" }, "geometry": { "type": "Point", "coordinates": [ 7.49863571343, 46.88888326683 ] } },
{ "type": "Feature", "properties": { "number": "8507079", "designationOfficial": "Bern Weissenbühl" }, "geometry": { "type": "Point", "coordinates": [ 7.43001881112, 46.935779356259999 ] } },
{ "type": "Feature", "properties": { "number": "8507078", "designationOfficial": "Wabern bei Bern" }, "geometry": { "type": "Point", "coordinates": [ 7.44588875523, 46.928662777169997 ] } },
{ "type": "Feature", "properties": { "number": "8507000", "designationOfficial": "Bern" }, "geometry": { "type": "Point", "coordinates": [ 7.43913088992, 46.9488322905 ] } },
{ "type": "Feature", "properties": { "number": "8516161", "designationOfficial": "Bern Wankdorf" }, "geometry": { "type": "Point", "coordinates": [ 7.46547780088, 46.967825765960001 ] } },
{ "type": "Feature", "properties": { "number": "8504441", "designationOfficial": "Studen BE" }, "geometry": { "type": "Point", "coordinates": [ 7.30081358676, 47.11158452574 ] } }
]
}
