{
"type": "FeatureCollection",
"name": "8505491",
"crs": { "type": "name", "properties": { "name": "urn:ogc:def:crs:OGC:1.3:CRS84" } },
"features": [
{ "type": "Feature", "properties": { "number": "8505491", "designationOfficial": "Tegna" }, "geometry": { "type": "Point", "coordinates": [ 8.742763671160001, 46.18602415806 ] } },
{ "type": "Feature", "properties": { "number": "8505493", "designationOfficial": "Cavigliano" }, "geometry": { "type": "Point", "coordinates": [ 8.721204104350001, 46.183760319279997 ] } },
{ "type": "Feature", "properties": { "number": "8505492", "designationOfficial": "Verscio" }, "geometry": { "type": "Point", "coordinates": [ 8.729477588110001, 46.18456262446 ] } },
{ "type": "Feature", "properties": { "number": "8505472", "designationOfficial": "Solduno" }, "geometry": { "type": "Point", "coordinates": [ 8.77760932104, 46.16947235109 ] } },
{ "type": "Feature", "properties": { "number": "8505494", "designationOfficial": "Intragna" }, "geometry": { "type": "Point", "coordinates": [ 8.70227000635, 46.177659996140001 ] } },
{ "type": "Feature", "properties": { "number": "8505496", "designationOfficial": "Verdasio" }, "geometry": { "type": "Point", "coordinates": [ 8.649199996829999, 46.165209995150001 ] } },
{ "type": "Feature", "properties": { "number": "8505499", "designationOfficial": "Camedo" }, "geometry": { "type": "Point", "coordinates": [ 8.61094488637, 46.154751302580003 ] } },
{ "type": "Feature", "properties": { "number": "8505400", "designationOfficial": "Locarno" }, "geometry": { "type": "Point", "coordinates": [ 8.801360899260001, 46.172420189439997 ] } },
{ "type": "Feature", "properties": { "number": "8505467", "designationOfficial": "Solduno S. Martino" }, "geometry": { "type": "Point", "coordinates": [ 8.77036999387, 46.171999996 ] } },
{ "type": "Feature", "properties": { "number": "8505471", "designationOfficial": "Locarno S. Antonio" }, "geometry": { "type": "Point", "coordinates": [ 8.78632297929, 46.16881913364 ] } }
]
}
