{
"type": "FeatureCollection",
"name": "8505003",
"crs": { "type": "name", "properties": { "name": "urn:ogc:def:crs:OGC:1.3:CRS84" } },
"features": [
{ "type": "Feature", "properties": { "number": "8505000", "designationOfficial": "Luzern" }, "geometry": { "type": "Point", "coordinates": [ 8.31018320694, 47.05017782809 ] } },
{ "type": "Feature", "properties": { "number": "8505003", "designationOfficial": "Immensee" }, "geometry": { "type": "Point", "coordinates": [ 8.46267203625, 47.0916186591 ] } },
{ "type": "Feature", "properties": { "number": "8505002", "designationOfficial": "Küssnacht am Rigi" }, "geometry": { "type": "Point", "coordinates": [ 8.433517457320001, 47.083594155219998 ] } },
{ "type": "Feature", "properties": { "number": "8505005", "designationOfficial": "Steinen" }, "geometry": { "type": "Point", "coordinates": [ 8.60744931426, 47.047668639260003 ] } },
{ "type": "Feature", "properties": { "number": "8505004", "designationOfficial": "Arth-Goldau" }, "geometry": { "type": "Point", "coordinates": [ 8.549446300670001, 47.049044883409998 ] } },
{ "type": "Feature", "properties": { "number": "8505018", "designationOfficial": "Meggen Zentrum" }, "geometry": { "type": "Point", "coordinates": [ 8.374393056840001, 47.045194446650001 ] } },
{ "type": "Feature", "properties": { "number": "8505007", "designationOfficial": "Brunnen" }, "geometry": { "type": "Point", "coordinates": [ 8.61006766101, 46.999174913140003 ] } },
{ "type": "Feature", "properties": { "number": "8505006", "designationOfficial": "Schwyz" }, "geometry": { "type": "Point", "coordinates": [ 8.632151708389999, 47.026397191039997 ] } },
{ "type": "Feature", "properties": { "number": "8505001", "designationOfficial": "Meggen" }, "geometry": { "type": "Point", "coordinates": [ 8.383061443880001, 47.050147795800001 ] } },
{ "type": "Feature", "properties": { "number": "8505011", "designationOfficial": "Merlischachen" }, "geometry": { "type": "Point", "coordinates": [ 8.40905814694, 47.067659984380001 ] } },
{ "type": "Feature", "properties": { "number": "8505111", "designationOfficial": "Sisikon" }, "geometry": { "type": "Point", "coordinates": [ 8.62074872767, 46.949254014570002 ] } },
{ "type": "Feature", "properties": { "number": "8505113", "designationOfficial": "Altdorf UR" }, "geometry": { "type": "Point", "coordinates": [ 8.631575417440001, 46.875738713280001 ] } },
{ "type": "Feature", "properties": { "number": "8505112", "designationOfficial": "Flüelen" }, "geometry": { "type": "Point", "coordinates": [ 8.62430265309, 46.901730165460002 ] } },
{ "type": "Feature", "properties": { "number": "8505114", "designationOfficial": "Erstfeld" }, "geometry": { "type": "Point", "coordinates": [ 8.65045464023, 46.820339408860001 ] } },
{ "type": "Feature", "properties": { "number": "8517336", "designationOfficial": "Luzern Verkehrshaus" }, "geometry": { "type": "Point", "coordinates": [ 8.33729732768, 47.053932316469997 ] } }
]
}
