{
"type": "FeatureCollection",
"name": "8507471",
"crs": { "type": "name", "properties": { "name": "urn:ogc:def:crs:OGC:1.3:CRS84" } },
"features": [
{ "type": "Feature", "properties": { "number": "8501609", "designationOfficial": "Brig" }, "geometry": { "type": "Point", "coordinates": [ 7.9880947394, 46.319422705779999 ] } },
{ "type": "Feature", "properties": { "number": "8504300", "designationOfficial": "Biel/Bienne" }, "geometry": { "type": "Point", "coordinates": [ 7.24291060323, 47.132897870859999 ] } },
{ "type": "Feature", "properties": { "number": "8504410", "designationOfficial": "Zollikofen" }, "geometry": { "type": "Point", "coordinates": [ 7.46291119582, 47.001825935440003 ] } },
{ "type": "Feature", "properties": { "number": "8504414", "designationOfficial": "Lyss" }, "geometry": { "type": "Point", "coordinates": [ 7.30630154849, 47.076323503929999 ] } },
{ "type": "Feature", "properties": { "number": "8507003", "designationOfficial": "Gümligen" }, "geometry": { "type": "Point", "coordinates": [ 7.50550479629, 46.934321918789998 ] } },
{ "type": "Feature", "properties": { "number": "8507002", "designationOfficial": "Ostermundigen" }, "geometry": { "type": "Point", "coordinates": [ 7.48149788168, 46.956802426449997 ] } },
{ "type": "Feature", "properties": { "number": "8507006", "designationOfficial": "Münsingen" }, "geometry": { "type": "Point", "coordinates": [ 7.55944239602, 46.873354149930002 ] } },
{ "type": "Feature", "properties": { "number": "8507471", "designationOfficial": "Eggerberg" }, "geometry": { "type": "Point", "coordinates": [ 7.88103271919, 46.306546298119997 ] } },
{ "type": "Feature", "properties": { "number": "8507470", "designationOfficial": "Lalden" }, "geometry": { "type": "Point", "coordinates": [ 7.90959226355, 46.301072866630001 ] } },
{ "type": "Feature", "properties": { "number": "8507481", "designationOfficial": "Mülenen" }, "geometry": { "type": "Point", "coordinates": [ 7.69131664681, 46.638028038450003 ] } },
{ "type": "Feature", "properties": { "number": "8507480", "designationOfficial": "Reichenbach im Kandertal" }, "geometry": { "type": "Point", "coordinates": [ 7.69006267569, 46.625121560069999 ] } },
{ "type": "Feature", "properties": { "number": "8507473", "designationOfficial": "Hohtenn" }, "geometry": { "type": "Point", "coordinates": [ 7.76408688742, 46.322458804919997 ] } },
{ "type": "Feature", "properties": { "number": "8507472", "designationOfficial": "Ausserberg" }, "geometry": { "type": "Point", "coordinates": [ 7.8441670281, 46.312348244939997 ] } },
{ "type": "Feature", "properties": { "number": "8507483", "designationOfficial": "Spiez" }, "geometry": { "type": "Point", "coordinates": [ 7.6801030578, 46.686395668350002 ] } },
{ "type": "Feature", "properties": { "number": "8507475", "designationOfficial": "Kandersteg" }, "geometry": { "type": "Point", "coordinates": [ 7.6714125588, 46.495396650540002 ] } },
{ "type": "Feature", "properties": { "number": "8507474", "designationOfficial": "Goppenstein" }, "geometry": { "type": "Point", "coordinates": [ 7.75492126836, 46.36770714811 ] } },
{ "type": "Feature", "properties": { "number": "8507478", "designationOfficial": "Frutigen" }, "geometry": { "type": "Point", "coordinates": [ 7.65141831454, 46.588907542809999 ] } },
{ "type": "Feature", "properties": { "number": "8507100", "designationOfficial": "Thun" }, "geometry": { "type": "Point", "coordinates": [ 7.62960582867, 46.754852730590002 ] } }
]
}
