{
"type": "FeatureCollection",
"name": "8507493",
"crs": { "type": "name", "properties": { "name": "urn:ogc:def:crs:OGC:1.3:CRS84" } },
"features": [
{ "type": "Feature", "properties": { "number": "8500010", "designationOfficial": "Basel SBB" }, "geometry": { "type": "Point", "coordinates": [ 7.58956279016, 47.547412055050003 ] } },
{ "type": "Feature", "properties": { "number": "8500218", "designationOfficial": "Olten" }, "geometry": { "type": "Point", "coordinates": [ 7.90769964791, 47.351934759270002 ] } },
{ "type": "Feature", "properties": { "number": "8500023", "designationOfficial": "Liestal" }, "geometry": { "type": "Point", "coordinates": [ 7.7313674807, 47.484461172129997 ] } },
{ "type": "Feature", "properties": { "number": "8500026", "designationOfficial": "Sissach" }, "geometry": { "type": "Point", "coordinates": [ 7.81202757047, 47.462754116859998 ] } },
{ "type": "Feature", "properties": { "number": "8500090", "designationOfficial": "Basel Bad Bf" }, "geometry": { "type": "Point", "coordinates": [ 7.60692041847, 47.567307905699998 ] } },
{ "type": "Feature", "properties": { "number": "8503000", "designationOfficial": "Zürich HB" }, "geometry": { "type": "Point", "coordinates": [ 8.539239, 47.378194 ] } },
{ "type": "Feature", "properties": { "number": "8503016", "designationOfficial": "Zürich Flughafen" }, "geometry": { "type": "Point", "coordinates": [ 8.56240182048, 47.450385629899998 ] } },
{ "type": "Feature", "properties": { "number": "8506000", "designationOfficial": "Winterthur" }, "geometry": { "type": "Point", "coordinates": [ 8.723821055409999, 47.500333810470003 ] } },
{ "type": "Feature", "properties": { "number": "8506100", "designationOfficial": "Frauenfeld" }, "geometry": { "type": "Point", "coordinates": [ 8.89655967341, 47.558163404570003 ] } },
{ "type": "Feature", "properties": { "number": "8506105", "designationOfficial": "Weinfelden" }, "geometry": { "type": "Point", "coordinates": [ 9.10636822199, 47.566224263229998 ] } },
{ "type": "Feature", "properties": { "number": "8506109", "designationOfficial": "Amriswil" }, "geometry": { "type": "Point", "coordinates": [ 9.30222720093, 47.550449721219998 ] } },
{ "type": "Feature", "properties": { "number": "8506121", "designationOfficial": "Romanshorn" }, "geometry": { "type": "Point", "coordinates": [ 9.37937129226, 47.565522864869997 ] } },
{ "type": "Feature", "properties": { "number": "8507000", "designationOfficial": "Bern" }, "geometry": { "type": "Point", "coordinates": [ 7.43913088992, 46.9488322905 ] } },
{ "type": "Feature", "properties": { "number": "8507006", "designationOfficial": "Münsingen" }, "geometry": { "type": "Point", "coordinates": [ 7.55944239602, 46.873354149930002 ] } },
{ "type": "Feature", "properties": { "number": "8507290", "designationOfficial": "Zweisimmen" }, "geometry": { "type": "Point", "coordinates": [ 7.37486190719, 46.553482551329999 ] } },
{ "type": "Feature", "properties": { "number": "8507298", "designationOfficial": "Wimmis" }, "geometry": { "type": "Point", "coordinates": [ 7.6355974518, 46.675722195939997 ] } },
{ "type": "Feature", "properties": { "number": "8507292", "designationOfficial": "Boltigen" }, "geometry": { "type": "Point", "coordinates": [ 7.39007365616, 46.627368255519997 ] } },
{ "type": "Feature", "properties": { "number": "8507297", "designationOfficial": "Oey-Diemtigen" }, "geometry": { "type": "Point", "coordinates": [ 7.57915212949, 46.659887768639997 ] } },
{ "type": "Feature", "properties": { "number": "8507296", "designationOfficial": "Erlenbach im Simmental" }, "geometry": { "type": "Point", "coordinates": [ 7.55523519614, 46.659091778319997 ] } },
{ "type": "Feature", "properties": { "number": "8507483", "designationOfficial": "Spiez" }, "geometry": { "type": "Point", "coordinates": [ 7.6801030578, 46.686395668350002 ] } },
{ "type": "Feature", "properties": { "number": "8507493", "designationOfficial": "Interlaken West" }, "geometry": { "type": "Point", "coordinates": [ 7.8514531376, 46.682627980360003 ] } },
{ "type": "Feature", "properties": { "number": "8507492", "designationOfficial": "Interlaken Ost" }, "geometry": { "type": "Point", "coordinates": [ 7.86900000435, 46.690499996189999 ] } },
{ "type": "Feature", "properties": { "number": "8507100", "designationOfficial": "Thun" }, "geometry": { "type": "Point", "coordinates": [ 7.62960582867, 46.754852730590002 ] } }
]
}
