{
"type": "FeatureCollection",
"name": "8509153",
"crs": { "type": "name", "properties": { "name": "urn:ogc:def:crs:OGC:1.3:CRS84" } },
"features": [
{ "type": "Feature", "properties": { "number": "8509000", "designationOfficial": "Chur" }, "geometry": { "type": "Point", "coordinates": [ 9.528937733039999, 46.853084162759998 ] } },
{ "type": "Feature", "properties": { "number": "8509157", "designationOfficial": "Arosa" }, "geometry": { "type": "Point", "coordinates": [ 9.67945480098, 46.783923530190002 ] } },
{ "type": "Feature", "properties": { "number": "8509155", "designationOfficial": "Langwies GR" }, "geometry": { "type": "Point", "coordinates": [ 9.707173048810001, 46.819600486330003 ] } },
{ "type": "Feature", "properties": { "number": "8509154", "designationOfficial": "Peist" }, "geometry": { "type": "Point", "coordinates": [ 9.671837614299999, 46.829721365559998 ] } },
{ "type": "Feature", "properties": { "number": "8509156", "designationOfficial": "Litzirüti" }, "geometry": { "type": "Point", "coordinates": [ 9.703213224380001, 46.79809733754 ] } },
{ "type": "Feature", "properties": { "number": "8509152", "designationOfficial": "Lüen-Castiel" }, "geometry": { "type": "Point", "coordinates": [ 9.61326295259, 46.831833593650003 ] } },
{ "type": "Feature", "properties": { "number": "8509153", "designationOfficial": "St. Peter-Molinis" }, "geometry": { "type": "Point", "coordinates": [ 9.65400511671, 46.829100300500002 ] } },
{ "type": "Feature", "properties": { "number": "8509150", "designationOfficial": "Chur Altstadt" }, "geometry": { "type": "Point", "coordinates": [ 9.53094841659, 46.847525490259997 ] } }
]
}
