{
"type": "FeatureCollection",
"name": "8511261",
"crs": { "type": "name", "properties": { "name": "urn:ogc:def:crs:OGC:1.3:CRS84" } },
"features": [
{ "type": "Feature", "properties": { "number": "8511261", "designationOfficial": "Sagliains Autoverlad" }, "geometry": { "type": "Point", "coordinates": [ 10.096529460239999, 46.763388273719997 ] } },
{ "type": "Feature", "properties": { "number": "8509095", "designationOfficial": "Klosters Selfranga" }, "geometry": { "type": "Point", "coordinates": [ 9.88384195741, 46.856078210909999 ] } }
]
}
